imglab/__init__.py
imglab/_version.py
imglab/color.py
imglab/position.py
imglab/sequence.py
imglab/signature.py
imglab/source.py
imglab/srcset.py
imglab/url.py
imglab/utils/__init__.py
imglab/utils/srcset.py
imglab/utils/url.py
imglab-0.2.0.dist-info/LICENSE
imglab-0.2.0.dist-info/METADATA
imglab-0.2.0.dist-info/WHEEL
imglab-0.2.0.dist-info/top_level.txt
imglab-0.2.0.dist-info/RECORD
