Metadata-Version: 2.1
Name: imglab
Version: 0.2.0
Summary: Official Python library to integrate with imglab services.
Author-email: imglab <support@imglab.io>
License: MIT License
Project-URL: Homepage, https://imglab.io
Project-URL: Source Code, https://github.com/imglab-io/imglab-py
Classifier: Programming Language :: Python :: 3.11
Classifier: Programming Language :: Python :: 3.10
Classifier: Programming Language :: Python :: 3.9
Classifier: Programming Language :: Python :: 3.8
Classifier: Programming Language :: Python :: 3.7
Classifier: Programming Language :: Python :: 3.6
Classifier: License :: OSI Approved :: MIT License
Classifier: Operating System :: OS Independent
Classifier: Intended Audience :: Developers
Requires-Python: >=3.6
License-File: LICENSE
